{"title":"[Classic] Anal Justice (1994) - Amanda Rae, Kristina West, Vict","uid":12207907,"size":603544551,"categoryP":"porn","categoryS":"movies","magnet":"?xt=urn:btih:1563b6aac6f90a2c7d2d8b64c53118dd284edd0a&amp;dn=+%5BClassic%5D+Anal+Justice+%281994%29+-+Amanda+Rae%2C+Kristina+West%2C+Vict&amp;tr=udp%3A%2F%2Ftracker.openbittorrent.com%3A80&amp;tr=udp%3A%2F%2Fopen.demonii.com%3A1337&amp;tr=udp%3A%2F%2Ftracker.coppersurfer.tk%3A6969&amp;tr=udp%3A%2F%2Fexodus.desync.com%3A6969","seeders":1,"leechers":2,"uploader":"Chinu685","files":1,"time":1439029184,"description":"\nAnal Justice\n\nThis incredibly hot collection of anal scenes will have you drooling for more. The fun starts with a steamy discovery, followed by a group of friends enjoying each other's company. Things stay hot with a juicy 3-way, and finishes off with a couple's romantic evening at home. All featuring in-your-face anal fun in the Rosebud tradition!\n\n &lt;a href=&quot;\nhttp://teenimage.org/img-55c5bc2c9b2f6.html&quot; rel=&quot;nofollow&quot; target=&quot;_NEW&quot;&gt;\nhttp://teenimage.org/img-55c5bc2c9b2f6.html&lt;/a&gt;\n\n\n\n..:For more awesome stuff click below:..          &lt;a href=&quot;\nhttps://thepiratebay.la/user/Chinu685/&quot; rel=&quot;nofollow&quot; target=&quot;_NEW&quot;&gt;\nhttps://thepiratebay.la/user/Chinu685/&lt;/a&gt;","torrent":{"xt":"urn:btih:1563b6aac6f90a2c7d2d8b64c53118dd284edd0a","amp;dn":"+%5BClassic%5D+Anal+Justice+%281994%29+-+Amanda+Rae%2C+Kristina+West%2C+Vict","amp;tr":["udp%3A%2F%2Ftracker.openbittorrent.com%3A80","udp%3A%2F%2Fopen.demonii.com%3A1337","udp%3A%2F%2Ftracker.coppersurfer.tk%3A6969","udp%3A%2F%2Fexodus.desync.com%3A6969"],"infoHash":"1563b6aac6f90a2c7d2d8b64c53118dd284edd0a","infoHashBuffer":{"type":"Buffer","data":[21,99,182,170,198,249,10,44,125,45,139,100,197,49,24,221,40,78,221,10]},"announce":[],"urlList":[]}}