{"title":"Eraserheads - Ang Huling El Bimbo","uid":9619494,"size":10837919,"categoryP":"audio","categoryS":"music","magnet":"?xt=urn:btih:2ef67874dfec621de934cad664b8a8b9fbb52d8a&amp;dn=Eraserheads+-+Ang+Huling+El+Bimbo&amp;tr=udp%3A%2F%2Ftracker.openbittorrent.com%3A80&amp;tr=udp%3A%2F%2Fopen.demonii.com%3A1337&amp;tr=udp%3A%2F%2Ftracker.coppersurfer.tk%3A6969&amp;tr=udp%3A%2F%2Fexodus.desync.com%3A6969","seeders":1,"leechers":0,"uploader":"richmondco","files":-1,"time":1392478216,"description":"Eraserheads - Ang Huling El Bimbo\n\n\nArtist: Eraserheads\nAlbum: Eraserheads Anthology\nGenre: Rock Ballad\nYear: 2004\nBitrate: 192 Kbps\n\nPlease continue seeding the torrent.\n\nDon't forget to leave your feedback.","torrent":{"xt":"urn:btih:2ef67874dfec621de934cad664b8a8b9fbb52d8a","amp;dn":"Eraserheads+-+Ang+Huling+El+Bimbo","amp;tr":["udp%3A%2F%2Ftracker.openbittorrent.com%3A80","udp%3A%2F%2Fopen.demonii.com%3A1337","udp%3A%2F%2Ftracker.coppersurfer.tk%3A6969","udp%3A%2F%2Fexodus.desync.com%3A6969"],"infoHash":"2ef67874dfec621de934cad664b8a8b9fbb52d8a","infoHashBuffer":{"type":"Buffer","data":[46,246,120,116,223,236,98,29,233,52,202,214,100,184,168,185,251,181,45,138]},"announce":[],"urlList":[]}}