{"title":"Leon Russell And The Shelter People (1971) (With bonus tracks)","uid":3240481,"size":90109433,"categoryP":"audio","categoryS":"music","magnet":"?xt=urn:btih:3b964766259066b7c40fc787bdbe02cdeb3bd590&amp;dn=Leon+Russell+And+The+Shelter+People+%281971%29+%28With+bonus+tracks%29&amp;tr=udp%3A%2F%2Ftracker.openbittorrent.com%3A80&amp;tr=udp%3A%2F%2Fopen.demonii.com%3A1337&amp;tr=udp%3A%2F%2Ftracker.coppersurfer.tk%3A6969&amp;tr=udp%3A%2F%2Fexodus.desync.com%3A6969","seeders":1,"leechers":13,"uploader":"Piozzi","files":14,"time":1095759458,"description":"Ripped at 224 AAC (.m4a), this seminal and sadly overlooked 1971 masterpiece needs a good seed. Check out the info at: http://www.superseventies.com/russellleon1.html\n\nNot that easy to find on CD; I actually had to buy my copy in a fierce eBay auction.\nLots of Dylan covers, too. :-)","torrent":{"xt":"urn:btih:3b964766259066b7c40fc787bdbe02cdeb3bd590","amp;dn":"Leon+Russell+And+The+Shelter+People+%281971%29+%28With+bonus+tracks%29","amp;tr":["udp%3A%2F%2Ftracker.openbittorrent.com%3A80","udp%3A%2F%2Fopen.demonii.com%3A1337","udp%3A%2F%2Ftracker.coppersurfer.tk%3A6969","udp%3A%2F%2Fexodus.desync.com%3A6969"],"infoHash":"3b964766259066b7c40fc787bdbe02cdeb3bd590","infoHashBuffer":{"type":"Buffer","data":[59,150,71,102,37,144,102,183,196,15,199,135,189,190,2,205,235,59,213,144]},"announce":[],"urlList":[]}}