{"title":"Mariusz Pudzianowski vs. Marcin Najman mma ufc 108","uid":5253670,"size":29740020,"categoryP":"video","categoryS":"movie_clips","magnet":"?xt=urn:btih:431384e07fb5c9e592e17a2ac16d7f6b2d922cc0&amp;dn=Mariusz+Pudzianowski+vs.+Marcin+Najman+mma+ufc+108&amp;tr=udp%3A%2F%2Ftracker.openbittorrent.com%3A80&amp;tr=udp%3A%2F%2Fopen.demonii.com%3A1337&amp;tr=udp%3A%2F%2Ftracker.coppersurfer.tk%3A6969&amp;tr=udp%3A%2F%2Fexodus.desync.com%3A6969","seeders":1,"leechers":0,"uploader":"willy5111","files":1,"time":1262459328,"description":"Mariusz Pudzianowski vs. Marcin Najman\n\nmma debut for both","torrent":{"xt":"urn:btih:431384e07fb5c9e592e17a2ac16d7f6b2d922cc0","amp;dn":"Mariusz+Pudzianowski+vs.+Marcin+Najman+mma+ufc+108","amp;tr":["udp%3A%2F%2Ftracker.openbittorrent.com%3A80","udp%3A%2F%2Fopen.demonii.com%3A1337","udp%3A%2F%2Ftracker.coppersurfer.tk%3A6969","udp%3A%2F%2Fexodus.desync.com%3A6969"],"infoHash":"431384e07fb5c9e592e17a2ac16d7f6b2d922cc0","infoHashBuffer":{"type":"Buffer","data":[67,19,132,224,127,181,201,229,146,225,122,42,193,109,127,107,45,146,44,192]},"announce":[],"urlList":[]}}