{"title":"Starbound Angry Koala -Update 7- (Windows,Linux,Mac)","uid":9386020,"size":1044107605,"categoryP":"games","categoryS":"mac","magnet":"?xt=urn:btih:5d17f7d8ca92bf96e13393fa3e39e75dd1d4b5ce&amp;dn=Starbound+Angry+Koala+-Update+7-+%28Windows%2CLinux%2CMac%29&amp;tr=udp%3A%2F%2Ftracker.openbittorrent.com%3A80&amp;tr=udp%3A%2F%2Fopen.demonii.com%3A1337&amp;tr=udp%3A%2F%2Ftracker.coppersurfer.tk%3A6969&amp;tr=udp%3A%2F%2Fexodus.desync.com%3A6969","seeders":1,"leechers":0,"uploader":"Vaaron","files":1,"time":1387758770,"description":"Starbound Angry Koala -Update 7-\n\nA ton of new content in this update. We've added a bunch of new features to world generation,\nwhich might require you to start on a new universe. To make sure you get access to all the new\ncrafting items you either need to unlock sectors again or create a new character.\n\nAlso..\n\n- Added skyrails based on Apjjms mod!\n- Added a brand new weather system, moddable weather/new environment effects\n- Hydrophobic objects are destroyed by all liquids\n- Trees can now be planted\n- Critical items stay on the ground longer\n- Some new monster behaviours\n- You must now be orbiting a planet to set it as your home\n- Free teleportation to home planet from ships teleporter\n- add acid rain, meteor showers, water collecting during storms and more\n- made species mods easier to combine with one another\n- add support for keysignature and keysignature changes for the abc system\n- Disable speedlimit for default projectiles to fix inaccurate bullets\n- New craftable turrets based on healthire's mod\n- You can now land on asteroid fields, based on hints mod\n- Tech now has descriptive instructions\n- Tons of Christmas stuff!!\n- Pos no longer 1 hit kill you\n- You can no longer breath on moons or asteroid fields without the proper equipment\n- Better fix fall damage\n- New barren planets perfect for building\n- Gravity now varies from planet to planet\n- Some planet backgrounds improved\n- Existing biomes can appear with different liquid types\n- You can now craft racial flags, to show you've been to a planet\n- NPCs will now switch to melee weapons up close\n- More random encounters\n- Pos can now be captured\n- Wiring station can now be built to access to a ton of different wiring tools\n- fixed mech legs\n- tons of server improvements\n\nAs Promised, I will keep Uploading the new version as soon as it releases. Thank You.","torrent":{"xt":"urn:btih:5d17f7d8ca92bf96e13393fa3e39e75dd1d4b5ce","amp;dn":"Starbound+Angry+Koala+-Update+7-+%28Windows%2CLinux%2CMac%29","amp;tr":["udp%3A%2F%2Ftracker.openbittorrent.com%3A80","udp%3A%2F%2Fopen.demonii.com%3A1337","udp%3A%2F%2Ftracker.coppersurfer.tk%3A6969","udp%3A%2F%2Fexodus.desync.com%3A6969"],"infoHash":"5d17f7d8ca92bf96e13393fa3e39e75dd1d4b5ce","infoHashBuffer":{"type":"Buffer","data":[93,23,247,216,202,146,191,150,225,51,147,250,62,57,231,93,209,212,181,206]},"announce":[],"urlList":[]}}