{"title":"Simon R. Green - Nightside-08-The Unnatural Inquirer","uid":11310885,"size":290446001,"categoryP":"audio","categoryS":"audio_books","magnet":"?xt=urn:btih:715e81af0d1dda713674d2c8854529e7befab354&amp;dn=Simon+R.+Green+-+Nightside-08-The+Unnatural+Inquirer&amp;tr=udp%3A%2F%2Ftracker.openbittorrent.com%3A80&amp;tr=udp%3A%2F%2Fopen.demonii.com%3A1337&amp;tr=udp%3A%2F%2Ftracker.coppersurfer.tk%3A6969&amp;tr=udp%3A%2F%2Fexodus.desync.com%3A6969","seeders":1,"leechers":0,"uploader":"twocows","files":12,"time":1414512866,"description":"Welcome to the Nightside, that secret square mile located in the dark heart of London where the sun never rises and people can fraternize with every myth and monster imaginable. John Taylor is a P.I. with the special ability to locate anyone or anything. &quot;The Unnatural Inquirer,&quot; the Nightside's most notorious gossip rag, has offered him a million pounds to find a DVD purportedto contain an actual recording of the afterlife. John doesn't know if it's true, but someone-or","torrent":{"xt":"urn:btih:715e81af0d1dda713674d2c8854529e7befab354","amp;dn":"Simon+R.+Green+-+Nightside-08-The+Unnatural+Inquirer","amp;tr":["udp%3A%2F%2Ftracker.openbittorrent.com%3A80","udp%3A%2F%2Fopen.demonii.com%3A1337","udp%3A%2F%2Ftracker.coppersurfer.tk%3A6969","udp%3A%2F%2Fexodus.desync.com%3A6969"],"infoHash":"715e81af0d1dda713674d2c8854529e7befab354","infoHashBuffer":{"type":"Buffer","data":[113,94,129,175,13,29,218,113,54,116,210,200,133,69,41,231,190,250,179,84]},"announce":[],"urlList":[]}}