{"title":"[ShesGonnaSquirt] Nikki Sexx, Jenna Presley (The Only Roommate /","uid":7677221,"size":649627810,"categoryP":"porn","categoryS":"movies","magnet":"?xt=urn:btih:7607076e0c4dea678562c38d10093dba4ea51aba&amp;dn=%5BShesGonnaSquirt%5D+Nikki+Sexx%2C+Jenna+Presley+%28The+Only+Roommate+%2F&amp;tr=udp%3A%2F%2Ftracker.openbittorrent.com%3A80&amp;tr=udp%3A%2F%2Fopen.demonii.com%3A1337&amp;tr=udp%3A%2F%2Ftracker.coppersurfer.tk%3A6969&amp;tr=udp%3A%2F%2Fexodus.desync.com%3A6969","seeders":1,"leechers":0,"uploader":"chkm8te","files":1,"time":1348726364,"description":"[ShesGonnaSquirt] Nikki Sexx, Jenna Presley (The Only Roommate / 27.09.2012)\n\nJenna and Nikki have a new roommate this week, Mr Johnny Sins. What sucks for him is that these two girls are stuck up selfish\nbitches that only like to shower with one another. All he's looking for is a little &quot;sexual healing&quot;. After sneaking up on them, they pay him\nback by &quot;Showering&quot; him down.\n\nScreens: &lt;a href=&quot;\nhttp://xxxhost.me/viewer.php?file=z7sz8ori8uut6ip1ob3j.jpg&quot; rel=&quot;nofollow&quot; target=&quot;_NEW&quot;&gt;\nhttp://xxxhost.me/viewer.php?file=z7sz8ori8uut6ip1ob3j.jpg&lt;/a&gt;\n &lt;a href=&quot;\nhttp://xxxhost.me/viewer.php?file=r60jpjos2xex85w0qd3v.jpg&quot; rel=&quot;nofollow&quot; target=&quot;_NEW&quot;&gt;\nhttp://xxxhost.me/viewer.php?file=r60jpjos2xex85w0qd3v.jpg&lt;/a&gt;","torrent":{"xt":"urn:btih:7607076e0c4dea678562c38d10093dba4ea51aba","amp;dn":"%5BShesGonnaSquirt%5D+Nikki+Sexx%2C+Jenna+Presley+%28The+Only+Roommate+%2F","amp;tr":["udp%3A%2F%2Ftracker.openbittorrent.com%3A80","udp%3A%2F%2Fopen.demonii.com%3A1337","udp%3A%2F%2Ftracker.coppersurfer.tk%3A6969","udp%3A%2F%2Fexodus.desync.com%3A6969"],"infoHash":"7607076e0c4dea678562c38d10093dba4ea51aba","infoHashBuffer":{"type":"Buffer","data":[118,7,7,110,12,77,234,103,133,98,195,141,16,9,61,186,78,165,26,186]},"announce":[],"urlList":[]}}