{"title":"David Guetta feat. Akon - Sexy B!tch [.mkv]","uid":5262374,"size":43336505,"categoryP":"video","categoryS":"music_videos","magnet":"?xt=urn:btih:7fb6f4843fa6177c02c1be178fae6c8db5b4d39d&amp;dn=David+Guetta+feat.+Akon+-+Sexy+B%21tch+%5B.mkv%5D&amp;tr=udp%3A%2F%2Ftracker.openbittorrent.com%3A80&amp;tr=udp%3A%2F%2Fopen.demonii.com%3A1337&amp;tr=udp%3A%2F%2Ftracker.coppersurfer.tk%3A6969&amp;tr=udp%3A%2F%2Fexodus.desync.com%3A6969","seeders":1,"leechers":0,"uploader":"barneyek","files":5,"time":1262736944,"description":"David Guetta feat. Akon - Sexy B!tch (Danceboy &amp; Silver Nikan Remix) (Supremo Videomix)\n\nVideo: MPEG4 Video (H264) 704x384 25.00fps\nAudio: MPEG Audio Layer 3 44100Hz Stereo\nTime: 4:03\n\nSupremo Ã‚Â© 2010","torrent":{"xt":"urn:btih:7fb6f4843fa6177c02c1be178fae6c8db5b4d39d","amp;dn":"David+Guetta+feat.+Akon+-+Sexy+B%21tch+%5B.mkv%5D","amp;tr":["udp%3A%2F%2Ftracker.openbittorrent.com%3A80","udp%3A%2F%2Fopen.demonii.com%3A1337","udp%3A%2F%2Ftracker.coppersurfer.tk%3A6969","udp%3A%2F%2Fexodus.desync.com%3A6969"],"infoHash":"7fb6f4843fa6177c02c1be178fae6c8db5b4d39d","infoHashBuffer":{"type":"Buffer","data":[127,182,244,132,63,166,23,124,2,193,190,23,143,174,108,141,181,180,211,157]},"announce":[],"urlList":[]}}