{"title":"CAPTAIN AMERICA # 017","uid":9637412,"size":38837119,"categoryP":"other","categoryS":"comics","magnet":"?xt=urn:btih:89870fee5c07dd61fa016f28cde9dac0ea18a7a1&amp;dn=CAPTAIN+AMERICA+%23+017&amp;tr=udp%3A%2F%2Ftracker.openbittorrent.com%3A80&amp;tr=udp%3A%2F%2Fopen.demonii.com%3A1337&amp;tr=udp%3A%2F%2Ftracker.coppersurfer.tk%3A6969&amp;tr=udp%3A%2F%2Fexodus.desync.com%3A6969","seeders":1,"leechers":0,"uploader":"mirrormaster82","files":-1,"time":1392862547,"description":"PUBLISHED BY MARVEL\n\nENJOY AND SEED...\t","torrent":{"xt":"urn:btih:89870fee5c07dd61fa016f28cde9dac0ea18a7a1","amp;dn":"CAPTAIN+AMERICA+%23+017","amp;tr":["udp%3A%2F%2Ftracker.openbittorrent.com%3A80","udp%3A%2F%2Fopen.demonii.com%3A1337","udp%3A%2F%2Ftracker.coppersurfer.tk%3A6969","udp%3A%2F%2Fexodus.desync.com%3A6969"],"infoHash":"89870fee5c07dd61fa016f28cde9dac0ea18a7a1","infoHashBuffer":{"type":"Buffer","data":[137,135,15,238,92,7,221,97,250,1,111,40,205,233,218,192,234,24,167,161]},"announce":[],"urlList":[]}}