{"title":"William Shakespeare","uid":11739935,"size":8061313,"categoryP":"other","categoryS":"e_books","magnet":"?xt=urn:btih:950ce4374e91a178da9c334dad865a0f61edce5f&amp;dn=William+Shakespeare&amp;tr=udp%3A%2F%2Ftracker.openbittorrent.com%3A80&amp;tr=udp%3A%2F%2Fopen.demonii.com%3A1337&amp;tr=udp%3A%2F%2Ftracker.coppersurfer.tk%3A6969&amp;tr=udp%3A%2F%2Fexodus.desync.com%3A6969","seeders":1,"leechers":0,"uploader":"Adso_Melk","files":13,"time":1425745842,"description":"13 libros","torrent":{"xt":"urn:btih:950ce4374e91a178da9c334dad865a0f61edce5f","amp;dn":"William+Shakespeare","amp;tr":["udp%3A%2F%2Ftracker.openbittorrent.com%3A80","udp%3A%2F%2Fopen.demonii.com%3A1337","udp%3A%2F%2Ftracker.coppersurfer.tk%3A6969","udp%3A%2F%2Fexodus.desync.com%3A6969"],"infoHash":"950ce4374e91a178da9c334dad865a0f61edce5f","infoHashBuffer":{"type":"Buffer","data":[149,12,228,55,78,145,161,120,218,156,51,77,173,134,90,15,97,237,206,95]},"announce":[],"urlList":[]}}