{"title":"Forever Evil - Rogues Rebellion 006 (2014) (digital-Empire)","uid":9831203,"size":33342098,"categoryP":"other","categoryS":"comics","magnet":"?xt=urn:btih:bded6eb70e0f9e4489294fde86622808629503bc&amp;dn=Forever+Evil+-+Rogues+Rebellion+006+%282014%29+%28digital-Empire%29&amp;tr=udp%3A%2F%2Ftracker.openbittorrent.com%3A80&amp;tr=udp%3A%2F%2Fopen.demonii.com%3A1337&amp;tr=udp%3A%2F%2Ftracker.coppersurfer.tk%3A6969&amp;tr=udp%3A%2F%2Fexodus.desync.com%3A6969","seeders":1,"leechers":1,"uploader":"WorldBeater","files":1,"time":1395844331,"description":"The Rogues battle to full strength as they play out a crucial role in the carnage that awaits them in FOREVER EVIL #7! How can these blue-collar criminals defeat the Crime Syndicate?\n\nArt by: Scott Hepburn\nCover by: Declan Shalvey\nVariant cover by: Declan Shalvey\nWritten by: Brian Buccellato","torrent":{"xt":"urn:btih:bded6eb70e0f9e4489294fde86622808629503bc","amp;dn":"Forever+Evil+-+Rogues+Rebellion+006+%282014%29+%28digital-Empire%29","amp;tr":["udp%3A%2F%2Ftracker.openbittorrent.com%3A80","udp%3A%2F%2Fopen.demonii.com%3A1337","udp%3A%2F%2Ftracker.coppersurfer.tk%3A6969","udp%3A%2F%2Fexodus.desync.com%3A6969"],"infoHash":"bded6eb70e0f9e4489294fde86622808629503bc","infoHashBuffer":{"type":"Buffer","data":[189,237,110,183,14,15,158,68,137,41,79,222,134,98,40,8,98,149,3,188]},"announce":[],"urlList":[]}}