{"title":"Arbitrage (2012) 1080p BluRay AC3+DTS HQ NL Subs","uid":7914782,"size":8745281617,"categoryP":"video","categoryS":"hd___movies","magnet":"?xt=urn:btih:d9994c27537165c3b4139ce2c5326537ccb568cf&amp;dn=Arbitrage+%282012%29+1080p+BluRay+AC3%2BDTS+HQ+NL+Subs&amp;tr=udp%3A%2F%2Ftracker.openbittorrent.com%3A80&amp;tr=udp%3A%2F%2Fopen.demonii.com%3A1337&amp;tr=udp%3A%2F%2Ftracker.coppersurfer.tk%3A6969&amp;tr=udp%3A%2F%2Fexodus.desync.com%3A6969","seeders":1,"leechers":1,"uploader":"NLUPPER002","files":-1,"time":1355351855,"description":"Arbitrage (2012) 1080p BluRay AC3+DTS HQ NL Subs\n.\n[IMG]http://i.imgur.com/4C88x.jpg[/IMG]\n.\nR 107 min  -  Drama | Thriller  -   24 January 2013 (Netherlands)\n. &lt;a href=&quot;\nhttp://www.imdb.com/title/tt1764183/&quot; rel=&quot;nofollow&quot; target=&quot;_NEW&quot;&gt;\nhttp://www.imdb.com/title/tt1764183/&lt;/a&gt;\n. &lt;a href=&quot;\nhttp://www.moviemeter.nl/film/81632&quot; rel=&quot;nofollow&quot; target=&quot;_NEW&quot;&gt;\nhttp://www.moviemeter.nl/film/81632&lt;/a&gt;\n.\nPLOT\n.\nA troubled hedge fund magnate desperate to complete the sale of his trading empire\nmakes an error that forces him to turn to an unlikely person for help.\n.\nHQ Dutch Subtitles White and yellow\nNL Vertaling: SRT-TEAM\n.\nFormat            : Matroska at 10.8 Mbps\nLength            : 8.14 GiB for 1h 47mn 28s 512ms\n\nVideo #0          : AVC at 8 686 Kbps\nAspect            : 1920 x 1080 (1.778) at 23.976 fps\n\nAudio #0          : DTS at 1 510 Kbps\nInfos             : 6 channels, 48.0 KHz\nLanguage          : en\n\nAudio #1          : AC-3 at 640 Kbps\nInfos             : 6 channels, 48.0 KHz\nLanguage          : en\n\nText #0           : VobSub HQ Wit\nLanguage          : nl\nText #1           : VobSub HQ Geel\nLanguage          : nl\nText #2           : UTF-8 Normaal SRT\nLanguage          : nl\n.\nEnjoy","torrent":{"xt":"urn:btih:d9994c27537165c3b4139ce2c5326537ccb568cf","amp;dn":"Arbitrage+%282012%29+1080p+BluRay+AC3%2BDTS+HQ+NL+Subs","amp;tr":["udp%3A%2F%2Ftracker.openbittorrent.com%3A80","udp%3A%2F%2Fopen.demonii.com%3A1337","udp%3A%2F%2Ftracker.coppersurfer.tk%3A6969","udp%3A%2F%2Fexodus.desync.com%3A6969"],"infoHash":"d9994c27537165c3b4139ce2c5326537ccb568cf","infoHashBuffer":{"type":"Buffer","data":[217,153,76,39,83,113,101,195,180,19,156,226,197,50,101,55,204,181,104,207]},"announce":[],"urlList":[]}}