{"title":"Blacked - Kristen Lee - Fit Brunette Girl Loves Black Dick","uid":14931487,"size":338697345,"categoryP":"porn","categoryS":"movie_clips","magnet":"?xt=urn:btih:dfc02618b3ffc7b447677b932350e7f31fffb356&amp;dn=Blacked+-+Kristen+Lee+-+Fit+Brunette+Girl+Loves+Black+Dick&amp;tr=udp%3A%2F%2Ftracker.leechers-paradise.org%3A6969&amp;tr=udp%3A%2F%2Fzer0day.ch%3A1337&amp;tr=udp%3A%2F%2Fopen.demonii.com%3A1337&amp;tr=udp%3A%2F%2Ftracker.coppersurfer.tk%3A6969&amp;tr=udp%3A%2F%2Fexodus.desync.com%3A6969","seeders":1,"leechers":0,"uploader":"gemini527nj","files":1,"time":1465960031,"description":"Blacked - Kristen Lee - Fit Brunette Girl Loves Black Dick (480P_1000)\r\n\r\nScreenshots:\r\n------------ \nhttp://xxxhost.me/viewer.php?file=5j3pb9lbfrqr57rogyke.jpg\r\n \nhttp://xxxhost.me/viewer.php?file=31pkgl5gn6d32gpy295q.jpg","torrent":{"xt":"urn:btih:dfc02618b3ffc7b447677b932350e7f31fffb356","amp;dn":"Blacked+-+Kristen+Lee+-+Fit+Brunette+Girl+Loves+Black+Dick","amp;tr":["udp%3A%2F%2Ftracker.leechers-paradise.org%3A6969","udp%3A%2F%2Fzer0day.ch%3A1337","udp%3A%2F%2Fopen.demonii.com%3A1337","udp%3A%2F%2Ftracker.coppersurfer.tk%3A6969","udp%3A%2F%2Fexodus.desync.com%3A6969"],"infoHash":"dfc02618b3ffc7b447677b932350e7f31fffb356","infoHashBuffer":{"type":"Buffer","data":[223,192,38,24,179,255,199,180,71,103,123,147,35,80,231,243,31,255,179,86]},"announce":[],"urlList":[]}}