{"title":"Marlango - Life in the treehouse (2010).","uid":5411873,"size":60237946,"categoryP":"audio","categoryS":"music","magnet":"?xt=urn:btih:e8e30105e676a1c16ca2291338a5289ef7f68847&amp;dn=Marlango+-+Life+in+the+treehouse+%282010%29.&amp;tr=udp%3A%2F%2Ftracker.openbittorrent.com%3A80&amp;tr=udp%3A%2F%2Fopen.demonii.com%3A1337&amp;tr=udp%3A%2F%2Ftracker.coppersurfer.tk%3A6969&amp;tr=udp%3A%2F%2Fexodus.desync.com%3A6969","seeders":1,"leechers":0,"uploader":"zurera","files":12,"time":1267782310,"description":"\n57 MB | Pop, Rock | 192 Kbps |\n\n\n\n1.The long fall\n2.I don't really want to know\n3.The answer\n4.Thank someone tonight\n5.You won't have me\n6.Play boy play\n7.White noise (secret sound)\n8.Let the sky fall\n9.I carry you\n10.Too many ways\n11.Take me\n*12. Lullaby (tema inÃƒÂ©dito sÃƒÂ³lo si se compra por itunes)*","torrent":{"xt":"urn:btih:e8e30105e676a1c16ca2291338a5289ef7f68847","amp;dn":"Marlango+-+Life+in+the+treehouse+%282010%29.","amp;tr":["udp%3A%2F%2Ftracker.openbittorrent.com%3A80","udp%3A%2F%2Fopen.demonii.com%3A1337","udp%3A%2F%2Ftracker.coppersurfer.tk%3A6969","udp%3A%2F%2Fexodus.desync.com%3A6969"],"infoHash":"e8e30105e676a1c16ca2291338a5289ef7f68847","infoHashBuffer":{"type":"Buffer","data":[232,227,1,5,230,118,161,193,108,162,41,19,56,165,40,158,247,246,136,71]},"announce":[],"urlList":[]}}