{"title":"Super 8 (2011) PAL Retail DD5.1 Eng Fr NL Subs","uid":6828064,"size":4658966354,"categoryP":"video","categoryS":"movies_dvdr","magnet":"?xt=urn:btih:fd1e15f695c57a7f2cf51146714229739ae37d1f&amp;dn=Super+8+%282011%29+PAL+Retail+DD5.1+Eng+Fr+NL+Subs&amp;tr=udp%3A%2F%2Ftracker.openbittorrent.com%3A80&amp;tr=udp%3A%2F%2Fopen.demonii.com%3A1337&amp;tr=udp%3A%2F%2Ftracker.coppersurfer.tk%3A6969&amp;tr=udp%3A%2F%2Fexodus.desync.com%3A6969","seeders":1,"leechers":0,"uploader":"NLUPPER002","files":69,"time":1321656458,"description":"Super 8 (2011) PAL Retail DD5.1 Eng Fr NL Subs\n.\n[IMG]http://img42.imageshack.us/img42/6216/70202.jpg[/IMG]\n.\nVerenigde Staten\nSciencefiction\n112 minuten\n\ngeregisseerd door J.J. Abrams\nmet Joel Courtney, Elle Fanning en Kyle Chandler\n\nIn de zomer van 1979 sluit de Amerikaanse Luchtmacht een sectie van Area 51. Alle materialen worden per trein vervoerd naar een opslagplaats in Ohio. De trein wordt echter aangereden door een truck en ontspoort. Een groepje kinderen, dat bezig is om hun eigen zombie-film te maken met hun 'Super 8' camera, stuit op de ravage. Al snel wordt vermoed dat het niet om een ongeluk gaat, als er plotseling verdwijningen plaatsvinden en onverklaarbare dingen gebeuren. Een lokale sheriff probeert het mysterie te ontrafelen, maar wil hij de angstaanjagende en onmenselijke waarheid wel weten?\n\nVanaf 22 november te huur\nVanaf 30 november te koop op DVD en Blu-Ray\n. &lt;a href=&quot;\nhttp://www.moviemeter.nl/film/70202&quot; rel=&quot;nofollow&quot; target=&quot;_NEW&quot;&gt;\nhttp://www.moviemeter.nl/film/70202&lt;/a&gt;\n.\nPLOT\n.\nDuring the summer of 1979, a group of friends witness a train crash and investigate subsequent unexplained events in their small town. \n. &lt;a href=&quot;\nhttp://www.imdb.com/title/tt1650062/&quot; rel=&quot;nofollow&quot; target=&quot;_NEW&quot;&gt;\nhttp://www.imdb.com/title/tt1650062/&lt;/a&gt;\n.\nINFO\n.\nSource: DVD9 PAL Retail\nFormat: DVD5\nVideo: PAL\nAudio: English, French DD5.1\nMenu: Yes\nSubs Retail English, Dutch, French\n.\nEnjoy\n","torrent":{"xt":"urn:btih:fd1e15f695c57a7f2cf51146714229739ae37d1f","amp;dn":"Super+8+%282011%29+PAL+Retail+DD5.1+Eng+Fr+NL+Subs","amp;tr":["udp%3A%2F%2Ftracker.openbittorrent.com%3A80","udp%3A%2F%2Fopen.demonii.com%3A1337","udp%3A%2F%2Ftracker.coppersurfer.tk%3A6969","udp%3A%2F%2Fexodus.desync.com%3A6969"],"infoHash":"fd1e15f695c57a7f2cf51146714229739ae37d1f","infoHashBuffer":{"type":"Buffer","data":[253,30,21,246,149,197,122,127,44,245,17,70,113,66,41,115,154,227,125,31]},"announce":[],"urlList":[]}}